mut/AuthenticationInfo.py
mut/__init__.py
mut/build_images.py
mut/convert_redirects.py
mut/helper.py
mut/intersphinx.py
mut/stage.py
mut/util.py
mut/index/Document.py
mut/index/Manifest.py
mut/index/MarianActions.py
mut/index/__init__.py
mut/index/main.py
mut/index/s3upload.py
mut/index/utils/AwaitResponse.py
mut/index/utils/IntroMessage.py
mut/index/utils/Logger.py
mut/index/utils/__init__.py
mut/redirects/__init__.py
mut/redirects/redirect_main.py
mut-0.9.2.dist-info/LICENSE
mut-0.9.2.dist-info/METADATA
mut-0.9.2.dist-info/WHEEL
mut-0.9.2.dist-info/entry_points.txt
mut-0.9.2.dist-info/top_level.txt
mut-0.9.2.dist-info/RECORD
