Metadata-Version: 2.1
Name: mut
Version: 0.9.2
Author: Andrew Aldridge
Author-email: i80and@foxquill.com
License: Apache
Classifier: Programming Language :: Python :: 3 :: Only
Classifier: License :: OSI Approved :: Apache Software License
Classifier: Topic :: Software Development :: Build Tools
Classifier: Topic :: Documentation
Classifier: Topic :: Text Processing
Requires-Python: >=3.5
License-File: LICENSE
Requires-Dist: boto3
Requires-Dist: certifi
Requires-Dist: cssselect
Requires-Dist: docopt
Requires-Dist: html5-parser
Requires-Dist: lxml
Requires-Dist: PyYAML
Requires-Dist: requests
